{
 "method": "neural NFSP (Heinrich & Silver 2016) on Leduc, exact NashConv",
 "feature_dim": 21,
 "config": {
  "hidden": 64,
  "eta": 0.1,
  "lr_rl": 0.01,
  "lr_sl": 0.01,
  "eps_start": 0.06,
  "eps_end": 0.0,
  "target_update": 1000
 },
 "n_seeds": 5,
 "checkpoints": [
  50000,
  100000,
  200000
 ],
 "uniform_exploitability": 4.747222222222217,
 "cfr_avg_final": 0.009423797486703389,
 "tabular_nfsp_curve": [
  {
   "episodes": 50000,
   "exploitability": 2.4037425552704477
  },
  {
   "episodes": 100000,
   "exploitability": 1.8015781993873259
  },
  {
   "episodes": 200000,
   "exploitability": 1.3435748005903458
  },
  {
   "episodes": 500000,
   "exploitability": 0.9640566489214734
  },
  {
   "episodes": 1000000,
   "exploitability": 0.8613560648756736
  }
 ],
 "per_seed": [
  {
   "seed": 0,
   "curve": [
    {
     "episodes": 50000,
     "exploitability": 1.540383404971684
    },
    {
     "episodes": 100000,
     "exploitability": 1.6012862748702896
    },
    {
     "episodes": 200000,
     "exploitability": 1.4528651899237788
    }
   ]
  },
  {
   "seed": 1,
   "curve": [
    {
     "episodes": 50000,
     "exploitability": 1.61061818467139
    },
    {
     "episodes": 100000,
     "exploitability": 1.590196380811389
    },
    {
     "episodes": 200000,
     "exploitability": 1.60109306725771
    }
   ]
  },
  {
   "seed": 2,
   "curve": [
    {
     "episodes": 50000,
     "exploitability": 2.0937298646828304
    },
    {
     "episodes": 100000,
     "exploitability": 1.90616226758597
    },
    {
     "episodes": 200000,
     "exploitability": 2.0897426577117595
    }
   ]
  },
  {
   "seed": 3,
   "curve": [
    {
     "episodes": 50000,
     "exploitability": 1.7826724418800954
    },
    {
     "episodes": 100000,
     "exploitability": 1.6537627583993777
    },
    {
     "episodes": 200000,
     "exploitability": 1.4737251068358943
    }
   ]
  },
  {
   "seed": 4,
   "curve": [
    {
     "episodes": 50000,
     "exploitability": 2.300386357712458
    },
    {
     "episodes": 100000,
     "exploitability": 1.765181136912074
    },
    {
     "episodes": 200000,
     "exploitability": 1.323893501734585
    }
   ]
  }
 ],
 "curve": [
  {
   "episodes": 50000,
   "mean_exploitability": 1.8655580507836915,
   "min": 1.540383404971684,
   "max": 2.300386357712458,
   "sd": 0.32355097857223497
  },
  {
   "episodes": 100000,
   "mean_exploitability": 1.70331776371582,
   "min": 1.590196380811389,
   "max": 1.90616226758597,
   "sd": 0.1328867377051839
  },
  {
   "episodes": 200000,
   "mean_exploitability": 1.5882639046927456,
   "min": 1.323893501734585,
   "max": 2.0897426577117595,
   "sd": 0.2970644649219527
  }
 ],
 "head_to_head": [
  {
   "episodes": 50000,
   "neural_mean": 1.8655580507836915,
   "tabular": 2.4037425552704477,
   "neural_beats_tabular": true
  },
  {
   "episodes": 100000,
   "neural_mean": 1.70331776371582,
   "tabular": 1.8015781993873259,
   "neural_beats_tabular": true
  },
  {
   "episodes": 200000,
   "neural_mean": 1.5882639046927456,
   "tabular": 1.3435748005903458,
   "neural_beats_tabular": false
  }
 ],
 "registered_in": "PREREGISTRATION.md \u00a711",
 "note": "Exact Leduc exploitability (NashConv), identical metric to the tabular learners. Neural NFSP generalises across info-sets via a 21-d feature; on this small game tabular is near-exact, so neural is expected to win on sample efficiency (matched-episode), not asymptotically. Reported in full per PREREGISTRATION.md \u00a78."
}